jax_smi/__init__.py
jax_smi/cli_tool.py
jax_smi/initialise_tracking.py
jax_smi-1.0.4.dist-info/LICENSE
jax_smi-1.0.4.dist-info/METADATA
jax_smi-1.0.4.dist-info/WHEEL
jax_smi-1.0.4.dist-info/entry_points.txt
jax_smi-1.0.4.dist-info/top_level.txt
jax_smi-1.0.4.dist-info/RECORD
