Metadata-Version: 2.1
Name: jax-smi
Version: 1.0.4
Summary: JAX Synergistic Memory Inspector
Author-email: Ayaka <ayaka@mail.shn.hk>
Project-URL: Homepage, https://github.com/ayaka14732/jax-smi
Project-URL: Issues, https://github.com/ayaka14732/jax-smi/issues
Classifier: Development Status :: 5 - Production/Stable
Classifier: Intended Audience :: Developers
Classifier: Intended Audience :: Education
Classifier: Intended Audience :: Science/Research
Classifier: License :: OSI Approved :: MIT License
Classifier: Topic :: Scientific/Engineering :: Mathematics
Classifier: Topic :: Scientific/Engineering :: Artificial Intelligence
Classifier: Topic :: Software Development :: Libraries :: Python Modules
Classifier: Topic :: System :: Distributed Computing
Classifier: Programming Language :: Python :: 3
Requires-Python: >=3.8
License-File: LICENSE
Requires-Dist: jax >=0.2.16
Requires-Dist: fire
